<?xml version="1.0" encoding="UTF-8"?>
<?xml-stylesheet type="text/xsl" href="configuration.xsl"?>

<configuration>
    <property>
        <name>new_user</name>
        <value>
            insert into `stats_user`
            (`date_dimension_id`,`platform_dimension_id`,`new_install_users`,`created`)
            values(?,?,?,?) on duplicate key update `new_install_users` = ?
        </value>
    </property>
    <property>
        <name>browser_new_user</name>
        <value>
            insert into `stats_device_browser`
            (`date_dimension_id`,`platform_dimension_id`,`browser_dimension_id`,`new_install_users`,`created`)
            values(?,?,?,?,?) on duplicate key update `new_install_users` = ?
        </value>
    </property>
    <property>
        <name>active_user</name>
        <value>
            insert into `stats_user`
            (`date_dimension_id`,`platform_dimension_id`,`new_install_users`,`created`)
            values(?,?,?,?) on duplicate key update `active_users` = ?
        </value>
    </property>
    <property>
        <name>browser_active_user</name>
        <value>
            insert into `stats_device_browser`
            (`date_dimension_id`,`platform_dimension_id`,`browser_dimension_id`,`new_install_users`,`created`)
            values(?,?,?,?,?) on duplicate key update `active_users` = ?
        </value>
    </property>
    <property>
        <name>active_member</name>
        <value>
            insert into `stats_user`
            (`date_dimension_id`,`platform_dimension_id`,`new_install_users`,`created`)
            values(?,?,?,?) on duplicate key update `active_members` = ?
        </value>
    </property>
    <property>
        <name>browser_active_member</name>
        <value>
            insert into `stats_device_browser`
            (`date_dimension_id`,`platform_dimension_id`,`browser_dimension_id`,`new_install_users`,`created`)
            values(?,?,?,?,?) on duplicate key update `active_members` = ?
        </value>
    </property>
    <property>
        <name>install_new_member</name>
        <value>
            insert into `member_info`
            (`member_id`,`last_visit_date`,`created`)
            values(?,?,?) on duplicate key update `last_visit_date` = ?
        </value>
    </property>
    <property>
        <name>new_member</name>
        <value>
            insert into `stats_user`
            (`date_dimension_id`,`platform_dimension_id`,`new_members`,`created`)
            values(?,?,?,?) on duplicate key update `new_members` = ?
        </value>
    </property>
    <property>
        <name>browser_new_member</name>
        <value>
            insert into `stats_device_browser`
            (`date_dimension_id`,`platform_dimension_id`,`browser_dimension_id`,`new_members`,`created`)
            values(?,?,?,?,?) on duplicate key update `new_members` = ?
        </value>
    </property>
</configuration>